amoeba2/__init__.py
amoeba2/_version.py
amoeba2/absorption_model.py
amoeba2/emission_absorption_model.py
amoeba2/physics.py
amoeba2/utils.py
amoeba2-1.1.1.dist-info/LICENSE
amoeba2-1.1.1.dist-info/METADATA
amoeba2-1.1.1.dist-info/WHEEL
amoeba2-1.1.1.dist-info/top_level.txt
amoeba2-1.1.1.dist-info/RECORD
