Metadata-Version: 2.1
Name: amoeba2
Version: 1.1.1
Summary: Automated Molecular Excitation Bayesian line-fitting Algorithm
Home-page: https://github.com/tvwenger/amoeba2
Author: Trey V. Wenger
Author-email: Trey Wenger <tvwenger@gmail.com>
License: The MIT License (MIT)
Project-URL: Homepage, https://github.com/tvwenger/amoeba2
Classifier: Programming Language :: Python :: 3
Classifier: License :: OSI Approved :: MIT License
Classifier: Operating System :: OS Independent
Requires-Python: >=3.11
License-File: LICENSE
Requires-Dist: astropy
Requires-Dist: astroquery
Requires-Dist: bayes_spec>=1.7.2
